pear/__init__.py
pear/collapse.py
pear/configuration.py
pear/do_nothing.py
pear/file_formatter.py
pear/layer.py
pear/loader.py
pear/main.py
pear/output_path.py
pear/remove.py
pear/replace.py
pear_cli-0.2.1.dist-info/METADATA
pear_cli-0.2.1.dist-info/WHEEL
pear_cli-0.2.1.dist-info/entry_points.txt
pear_cli-0.2.1.dist-info/top_level.txt
pear_cli-0.2.1.dist-info/RECORD
