Metadata-Version: 2.1
Name: pear-cli
Version: 0.2.1
Summary: A utility for generating variations of source code for docmentation
Home-page: https://github.com/chiptopher/pear
License: UNKNOWN
Keywords: file generation
Platform: UNKNOWN
